refstack/__init__.py
refstack/opts.py
refstack/api/__init__.py
refstack/api/app.py
refstack/api/app.wsgi
refstack/api/config.py
refstack/api/constants.py
refstack/api/exceptions.py
refstack/api/guidelines.py
refstack/api/utils.py
refstack/api/validators.py
refstack/api/controllers/__init__.py
refstack/api/controllers/auth.py
refstack/api/controllers/guidelines.py
refstack/api/controllers/products.py
refstack/api/controllers/results.py
refstack/api/controllers/root.py
refstack/api/controllers/user.py
refstack/api/controllers/v1.py
refstack/api/controllers/validation.py
refstack/api/controllers/vendors.py
refstack/db/__init__.py
refstack/db/api.py
refstack/db/migration.py
refstack/db/utils.py
refstack/db/migrations/__init__.py
refstack/db/migrations/alembic.ini
refstack/db/migrations/alembic/README
refstack/db/migrations/alembic/__init__.py
refstack/db/migrations/alembic/env.py
refstack/db/migrations/alembic/migration.py
refstack/db/migrations/alembic/script.py.mako
refstack/db/migrations/alembic/utils.py
refstack/db/migrations/alembic/versions/19fded785b8c_create_organization_table.py
refstack/db/migrations/alembic/versions/23843be3da52_add_product_version_id.py
refstack/db/migrations/alembic/versions/2f178b0bf762_create_user_table.py
refstack/db/migrations/alembic/versions/319ee8fe47c7_create_group_table.py
refstack/db/migrations/alembic/versions/35bf54e2c13c_add_product_version.py
refstack/db/migrations/alembic/versions/42278d6179b9_init.py
refstack/db/migrations/alembic/versions/428e5aef5534_associate_test_result.py
refstack/db/migrations/alembic/versions/434be17a6ec3_fix_openids_with_space.py
refstack/db/migrations/alembic/versions/534e20be9964_create_pubkey_table.py
refstack/db/migrations/alembic/versions/59df512e82f_add_verification_status.py
refstack/db/migrations/alembic/versions/7092392cbb8e_create_product_table.py
refstack/db/migrations/alembic/versions/7093ca478d35_product_table_make_product_id_nullable.py
refstack-2.1.0.dist-info/AUTHORS
refstack-2.1.0.dist-info/LICENSE
refstack-2.1.0.dist-info/METADATA
refstack-2.1.0.dist-info/WHEEL
refstack-2.1.0.dist-info/entry_points.txt
refstack-2.1.0.dist-info/pbr.json
refstack-2.1.0.dist-info/top_level.txt
refstack-2.1.0.dist-info/RECORD
