Metadata-Version: 2.1
Name: refstack
Version: 2.1.0
Summary: OpenStack interop testing
Home-page: https://refstack.openstack.org
Author: OpenStack
Author-email: openstack-discuss@lists.openstack.org
License: UNKNOWN
Platform: UNKNOWN
Classifier: Environment :: OpenStack
Classifier: Intended Audience :: Developers
Classifier: Intended Audience :: Information Technology
Classifier: License :: OSI Approved :: Apache Software License
Classifier: Operating System :: POSIX :: Linux
Classifier: Programming Language :: Python
Classifier: Programming Language :: Python :: 3
Classifier: Programming Language :: Python :: 3.8
Classifier: Programming Language :: Python :: 3.9
Classifier: Programming Language :: Python :: 3.10
Classifier: Programming Language :: Python :: 3 :: Only
Classifier: Programming Language :: Python :: Implementation :: CPython
Requires-Python: >=3.8
Requires-Dist: PyJWT (>=2.0.0)
Requires-Dist: PyMySQL (!=0.6.4,>=0.6.2)
Requires-Dist: SQLAlchemy (>=0.8.3)
Requires-Dist: WebOb (>=1.7.1)
Requires-Dist: alembic (>=1.8.0)
Requires-Dist: beaker
Requires-Dist: beautifulsoup4
Requires-Dist: cryptography (>=3.0)
Requires-Dist: docutils (>=0.11)
Requires-Dist: jsonschema (>=4.7.0)
Requires-Dist: oslo.config (>=1.6.0)
Requires-Dist: oslo.db (>=1.4.1)
Requires-Dist: oslo.log (>=3.11.0)
Requires-Dist: oslo.utils (>=3.16.0)
Requires-Dist: pecan (>=0.8.2)
Requires-Dist: requests (!=2.4.0,>=2.2.0)
Requires-Dist: requests-cache (<0.6.0,>=0.4.9)
